{
  "type": "FeatureCollection",
  "crs": {
    "type": "name",
    "properties": { "name": "Event Data: EDM Night Toronto" }
  },
  "features": [
    {
      "type": "Feature",
      "properties": {
        "PARK_ID": 1160,
        "FACILITYID": 28007,
        "NAME": "Whyte Ave",
        "DATE": "27th January 2020",
        "LOCATION": "Yonge-Dundas Square Toronto",
        "HOURS": "6PM-10PM",
        "ACCESS_TYPES": "STAFF and ARTISTS ONLY",
        "ZONE_TYPE": "IN",
        "ENTRACE_CONNCTED":true,
        "NEAREST_ENTRANCE": "1",
        "BAR": true,
        "FOOD": true,
        "LANES": 10,
        "DESCRIPTIO": "Main street for city of Strathcona, known for pubs and restaurants."
      },
      "geometry": {
        "type": "Point",
        "coordinates": [53.5180008,-113.4716744]
      }
    },
    {
      "type": "Feature",
      "properties": {
        "PARK_ID": 1693,
        "FACILITYID": 28016,
        "NAME": "DICE",
        "DATE": "7th January 2023",
        "LOCATION": "University of Alberta",
        "HOURS": "6PM-10PM",
        "ACCESS_TYPES": "STAFF and STUDENTS ONLY",
        "ZONE_TYPE": "IN",
        "ENTRACE_CONNCTED":true,
        "NEAREST_ENTRANCE": "1",
        "BAR": true,
        "FOOD": true,
        "LANES": 10,
        "DESCRIPTIO": "The Donadeo Innovation Centre for Engineering."
      },
      "geometry": {
        "type": "Point",
        "coordinates": [53.5282209,-113.5296782]
      }
    }

  ]
}